netlink/sap/rfc/__init__.py
netlink/sap/rfc/connection/__init__.py
netlink/sap/rfc/connection/application_server.py
netlink/sap/rfc/connection/connection.py
netlink/sap/rfc/connection/dest.py
netlink/sap/rfc/connection/keepass.py
netlink/sap/rfc/connection/landscape/__init__.py
netlink/sap/rfc/connection/landscape/get_landscape_files.py
netlink/sap/rfc/connection/landscape/landscape.py
netlink/sap/rfc/connection/landscape/process_landscape_xml.py
netlink/sap/rfc/connection/login.py
netlink/sap/rfc/connection/login_sid.py
netlink/sap/rfc/connection/server.py
netlink/sap/rfc/connection/sso.py
netlink/sap/rfc/connection/util.py
netlink/sap/rfc/exception.py
netlink/sap/rfc/function.py
netlink/sap/rfc/table.py
netlink/sap/rfc/util.py
netlink_sap_rfc-0.1.17.dist-info/LICENSE.md
netlink_sap_rfc-0.1.17.dist-info/WHEEL
netlink_sap_rfc-0.1.17.dist-info/METADATA
netlink_sap_rfc-0.1.17.dist-info/RECORD
