Metadata-Version: 2.1
Name: netlink-sap-rfc
Version: 0.1.17
Summary: Access SAP via RFC
Home-page: https://gitlab.com/netlink-consulting/netlink-sap-rfc
License: MIT
Keywords: sap rfc
Author: Bernhard Radermacher
Author-email: bernhard.radermacher@netlink-consulting.com
Requires-Python: >=3.8,<3.13
Classifier: License :: OSI Approved :: MIT License
Classifier: Programming Language :: Python :: 3
Classifier: Programming Language :: Python :: 3.10
Classifier: Programming Language :: Python :: 3.8
Classifier: Programming Language :: Python :: 3.9
Classifier: Topic :: Software Development
Requires-Dist: lxml (>=4.9.1,<5.0.0)
Requires-Dist: netlink-logging (>=0.1.9,<0.2.0)
Requires-Dist: pyrfc (>=3.3,<4.0)
Project-URL: Repository, https://gitlab.com/netlink-consulting/netlink-sap-rfc
